hug_middleware_cors.py
hug_middleware_cors-1.0.0.dist-info/DESCRIPTION.rst
hug_middleware_cors-1.0.0.dist-info/METADATA
hug_middleware_cors-1.0.0.dist-info/RECORD
hug_middleware_cors-1.0.0.dist-info/WHEEL
hug_middleware_cors-1.0.0.dist-info/metadata.json
hug_middleware_cors-1.0.0.dist-info/top_level.txt
