Metadata-Version: 2.0
Name: hug-middleware-cors
Version: 1.0.0
Summary: CORS middleware for the hug framework
Home-page: https://github.com/sseemayer/hug_middleware_cors
Author: Stefan Seemayer
Author-email: stefan@seemayer.de
License: MIT
Keywords: hug cors middleware access-control-allow-origin
Platform: UNKNOWN
Classifier: Development Status :: 4 - Beta
Classifier: Intended Audience :: Developers
Classifier: Topic :: Internet :: WWW/HTTP :: WSGI :: Middleware
Classifier: License :: OSI Approved :: MIT License
Classifier: Programming Language :: Python :: 3
Classifier: Programming Language :: Python :: 3 :: Only
Classifier: Programming Language :: Python :: 3.3
Classifier: Programming Language :: Python :: 3.4
Classifier: Programming Language :: Python :: 3.5
Classifier: Programming Language :: Python :: 3.6
Requires-Dist: hug
